<?xml version='1.0' encoding='UTF-8'?>
<fingerprint>
  <timestamp>2017-08-11 09:07:17.293 UTC</timestamp>
  <original>
    <name>jpetstore/org.mybatis:jpetstore</name>
    <number>9</number>
  </original>
  <md5sum>b4c3ba17e0ae691d9825756445d513ed</md5sum>
  <fileName>org.mybatis:jpetstore.war</fileName>
  <usages>
    <entry>
      <string>jpetstore</string>
      <ranges>9</ranges>
    </entry>
    <entry>
      <string>jpetstore/org.mybatis:jpetstore</string>
      <ranges>9</ranges>
    </entry>
  </usages>
  <facets/>
</fingerprint>