<?xml version='1.0' encoding='UTF-8'?>
<fingerprint>
  <timestamp>2017-08-27 13:06:18.405 UTC</timestamp>
  <original>
    <name>jpetstore/org.mybatis:jpetstore</name>
    <number>13</number>
  </original>
  <md5sum>1886716af564f10a9335f111bedb9510</md5sum>
  <fileName>org.mybatis:jpetstore.war</fileName>
  <usages>
    <entry>
      <string>jpetstore</string>
      <ranges>13</ranges>
    </entry>
    <entry>
      <string>jpetstore/org.mybatis:jpetstore</string>
      <ranges>13</ranges>
    </entry>
  </usages>
  <facets/>
</fingerprint>